Py2Web/__init__.py
Py2Web/browser.py
Py2Web/config.py
Py2Web/main.py
Py2Web/engine/Py2WebProfile.py
Py2Web/engine/__init__.py
Py2Web/utils/__init__.py
Py2Web/utils/xvfb.py
Py2Web-1.0.6.dist-info/LICENSE
Py2Web-1.0.6.dist-info/METADATA
Py2Web-1.0.6.dist-info/WHEEL
Py2Web-1.0.6.dist-info/top_level.txt
Py2Web-1.0.6.dist-info/RECORD
