Metadata-Version: 2.1
Name: Py2Web
Version: 1.0.6
Summary: A python package to perform HTTP requests to websites and render their content.
Home-page: https://github.com/iiestIT/Py2Web
Author: iiestIT
Author-email: it.iiest.de@gmail.com
License: UNKNOWN
Keywords: pyside2 browser engine rendering
Platform: UNKNOWN
Classifier: Development Status :: 2 - Pre-Alpha
Classifier: Programming Language :: Python :: 3
Classifier: Programming Language :: Python :: 3.9
Classifier: Topic :: Internet :: WWW/HTTP :: Browsers
Requires-Python: >=3.8
Requires-Dist: pyside2
Requires-Dist: xvfbwrapper
